huoshui_pdf_converter/__init__.py
huoshui_pdf_converter/__main__.py
huoshui_pdf_converter/cli.py
huoshui_pdf_converter/markdown_converter.py
huoshui_pdf_converter/pdf_converter.py
huoshui_pdf_converter/py.typed
huoshui_pdf_converter/server.py
huoshui_pdf_converter-1.0.4.dist-info/METADATA
huoshui_pdf_converter-1.0.4.dist-info/WHEEL
huoshui_pdf_converter-1.0.4.dist-info/entry_points.txt
huoshui_pdf_converter-1.0.4.dist-info/licenses/LICENSE
huoshui_pdf_converter-1.0.4.dist-info/RECORD
