Metadata-Version: 2.4
Name: huoshui-pdf-converter
Version: 1.0.4
Summary: High-quality PDF ↔ Markdown converter with MCP integration and Unicode support
Project-URL: Homepage, https://github.com/yourusername/huoshui-pdf-converter
Project-URL: Repository, https://github.com/yourusername/huoshui-pdf-converter
Project-URL: Issues, https://github.com/yourusername/huoshui-pdf-converter/issues
Project-URL: Documentation, https://github.com/yourusername/huoshui-pdf-converter#readme
Project-URL: Changelog, https://github.com/yourusername/huoshui-pdf-converter/releases
Author-email: Huoshui Development Team <dev@huoshui.ai>
Maintainer-email: Huoshui Development Team <dev@huoshui.ai>
License: MIT
License-File: LICENSE
Keywords: chinese,cjk,converter,markdown,mcp,pdf,unicode
Classifier: Development Status :: 5 - Production/Stable
Classifier: Intended Audience :: Developers
Classifier: Intended Audience :: End Users/Desktop
Classifier: License :: OSI Approved :: MIT License
Classifier: Natural Language :: Chinese (Simplified)
Classifier: Natural Language :: English
Classifier: Operating System :: OS Independent
Classifier: Programming Language :: Python :: 3
Classifier: Programming Language :: Python :: 3.10
Classifier: Programming Language :: Python :: 3.11
Classifier: Programming Language :: Python :: 3.12
Classifier: Topic :: Office/Business :: Office Suites
Classifier: Topic :: Text Processing :: Markup
Classifier: Topic :: Text Processing :: Markup :: Markdown
Classifier: Topic :: Utilities
Classifier: Typing :: Typed
Requires-Python: >=3.10
Requires-Dist: fastmcp>=2.10.0
Requires-Dist: fpdf2>=2.8.3
Requires-Dist: markdown>=3.8.0
Requires-Dist: mcp>=1.10.0
Requires-Dist: pillow>=11.0.0
Requires-Dist: pymupdf>=1.26.0
Requires-Dist: reportlab>=4.4.0
Requires-Dist: xhtml2pdf>=0.2.17
Provides-Extra: all
Requires-Dist: black>=23.0.0; extra == 'all'
Requires-Dist: build>=1.0.0; extra == 'all'
Requires-Dist: mypy>=1.0.0; extra == 'all'
Requires-Dist: pytest-asyncio>=0.21.0; extra == 'all'
Requires-Dist: pytest>=7.0.0; extra == 'all'
Requires-Dist: ruff>=0.1.0; extra == 'all'
Requires-Dist: twine>=4.0.0; extra == 'all'
Provides-Extra: dev
Requires-Dist: black>=23.0.0; extra == 'dev'
Requires-Dist: build>=1.0.0; extra == 'dev'
Requires-Dist: mypy>=1.0.0; extra == 'dev'
Requires-Dist: pytest-asyncio>=0.21.0; extra == 'dev'
Requires-Dist: pytest>=7.0.0; extra == 'dev'
Requires-Dist: ruff>=0.1.0; extra == 'dev'
Requires-Dist: twine>=4.0.0; extra == 'dev'
